{
  "name": "Youtube automation",
  "nodes": [
    {
      "parameters": {},
      "type": "n8n-nodes-base.manualTrigger",
      "typeVersion": 1,
      "position": [
        -832,
        -96
      ],
      "id": "07dc138e-9992-4029-b7a4-94a5b6a271cd",
      "name": "When clicking ‘Execute workflow’"
    },
    {
      "parameters": {
        "rule": {
          "interval": [
            {}
          ]
        }
      },
      "type": "n8n-nodes-base.scheduleTrigger",
      "typeVersion": 1.2,
      "position": [
        -816,
        112
      ],
      "id": "fb35f712-320e-4f19-b73c-0e21327c81fe",
      "name": "Schedule Trigger"
    },
    {
      "parameters": {
        "documentId": {
          "__rl": true,
          "value": "1pYTWAISiULlGLZbFIKaNT10vb4Zc9EboIotT1T8XHcY",
          "mode": "list",
          "cachedResultName": "Videos List",
          "cachedResultUrl": "https://docs.google.com/spreadsheets/d/1pYTWAISiULlGLZbFIKaNT10vb4Zc9EboIotT1T8XHcY/edit?usp=drivesdk"
        },
        "sheetName": {
          "__rl": true,
          "value": "gid=0",
          "mode": "list",
          "cachedResultName": "Sheet1",
          "cachedResultUrl": "https://docs.google.com/spreadsheets/d/1pYTWAISiULlGLZbFIKaNT10vb4Zc9EboIotT1T8XHcY/edit#gid=0"
        },
        "filtersUI": {
          "values": [
            {
              "lookupColumn": "Video Status",
              "lookupValue": "To Publish"
            }
          ]
        },
        "options": {
          "returnFirstMatch": true
        }
      },
      "type": "n8n-nodes-base.googleSheets",
      "typeVersion": 4.7,
      "position": [
        -528,
        16
      ],
      "id": "0610e41f-0bc1-4a03-a49d-72c342745708",
      "name": "Get row(s) in sheet",
      "credentials": {
        "googleSheetsOAuth2Api": {
          "id": "vuugbC8pFk62rio0",
          "name": "Google Sheets account"
        }
      }
    },
    {
      "parameters": {
        "resource": "fileFolder",
        "queryString": "={{ $json['File Name'] }}",
        "filter": {
          "folderId": {
            "__rl": true,
            "value": "1e4Qnr1kwMGTp3pKkzkJok7W-rGPoSeJN",
            "mode": "list",
            "cachedResultName": "Videos shorts",
            "cachedResultUrl": "https://drive.google.com/drive/folders/1e4Qnr1kwMGTp3pKkzkJok7W-rGPoSeJN"
          }
        },
        "options": {}
      },
      "type": "n8n-nodes-base.googleDrive",
      "typeVersion": 3,
      "position": [
        -336,
        16
      ],
      "id": "b40d309d-fafc-4bea-b6a4-8f1a54283d92",
      "name": "Search files and folders",
      "credentials": {
        "googleDriveOAuth2Api": {
          "id": "HJkfeps1RZVq0lmo",
          "name": "Google Drive account"
        }
      }
    },
    {
      "parameters": {
        "operation": "download",
        "fileId": {
          "__rl": true,
          "value": "={{ $json.id }}",
          "mode": "id"
        },
        "options": {}
      },
      "type": "n8n-nodes-base.googleDrive",
      "typeVersion": 3,
      "position": [
        -160,
        16
      ],
      "id": "1643b655-bea3-4346-93fd-d542fd682692",
      "name": "Download file",
      "credentials": {
        "googleDriveOAuth2Api": {
          "id": "HJkfeps1RZVq0lmo",
          "name": "Google Drive account"
        }
      }
    },
    {
      "parameters": {
        "resource": "video",
        "operation": "upload",
        "title": "={{ $('Get row(s) in sheet').first().json['Youtube Title'] }}",
        "regionCode": "PK",
        "categoryId": "27",
        "options": {
          "description": "={{ $('Get row(s) in sheet').item.json['Youtube Description'] }}",
          "privacyStatus": "public",
          "tags": "={{ $('Get row(s) in sheet').item.json['Youtube Tags'] }}"
        }
      },
      "type": "n8n-nodes-base.youTube",
      "typeVersion": 1,
      "position": [
        16,
        16
      ],
      "id": "ae6943e3-0cd1-4eed-aa5e-cd1301261a13",
      "name": "Upload a video",
      "credentials": {
        "youTubeOAuth2Api": {
          "id": "j4N3KIHznjPo5Tob",
          "name": "YouTube account"
        }
      }
    },
    {
      "parameters": {
        "operation": "update",
        "documentId": {
          "__rl": true,
          "value": "1pYTWAISiULlGLZbFIKaNT10vb4Zc9EboIotT1T8XHcY",
          "mode": "list",
          "cachedResultName": "Videos List",
          "cachedResultUrl": "https://docs.google.com/spreadsheets/d/1pYTWAISiULlGLZbFIKaNT10vb4Zc9EboIotT1T8XHcY/edit?usp=drivesdk"
        },
        "sheetName": {
          "__rl": true,
          "value": "gid=0",
          "mode": "list",
          "cachedResultName": "Sheet1",
          "cachedResultUrl": "https://docs.google.com/spreadsheets/d/1pYTWAISiULlGLZbFIKaNT10vb4Zc9EboIotT1T8XHcY/edit#gid=0"
        },
        "columns": {
          "mappingMode": "defineBelow",
          "value": {
            "row_number": 0,
            "ID": "={{ $('Get row(s) in sheet').first().json.ID }}",
            "Video Status": "Published"
          },
          "matchingColumns": [
            "ID"
          ],
          "schema": [
            {
              "id": "ID",
              "displayName": "ID",
              "required": false,
              "defaultMatch": false,
              "display": true,
              "type": "string",
              "canBeUsedToMatch": true,
              "removed": false
            },
            {
              "id": "Topic",
              "displayName": "Topic",
              "required": false,
              "defaultMatch": false,
              "display": true,
              "type": "string",
              "canBeUsedToMatch": true,
              "removed": false
            },
            {
              "id": "File Name",
              "displayName": "File Name",
              "required": false,
              "defaultMatch": false,
              "display": true,
              "type": "string",
              "canBeUsedToMatch": true,
              "removed": false
            },
            {
              "id": "Youtube Title",
              "displayName": "Youtube Title",
              "required": false,
              "defaultMatch": false,
              "display": true,
              "type": "string",
              "canBeUsedToMatch": true,
              "removed": false
            },
            {
              "id": "Youtube Description",
              "displayName": "Youtube Description",
              "required": false,
              "defaultMatch": false,
              "display": true,
              "type": "string",
              "canBeUsedToMatch": true,
              "removed": false
            },
            {
              "id": "Youtube Tags",
              "displayName": "Youtube Tags",
              "required": false,
              "defaultMatch": false,
              "display": true,
              "type": "string",
              "canBeUsedToMatch": true,
              "removed": false
            },
            {
              "id": "Video Status",
              "displayName": "Video Status",
              "required": false,
              "defaultMatch": false,
              "display": true,
              "type": "string",
              "canBeUsedToMatch": true,
              "removed": false
            },
            {
              "id": "row_number",
              "displayName": "row_number",
              "required": false,
              "defaultMatch": false,
              "display": true,
              "type": "number",
              "canBeUsedToMatch": true,
              "readOnly": true,
              "removed": false
            }
          ],
          "attemptToConvertTypes": false,
          "convertFieldsToString": false
        },
        "options": {}
      },
      "type": "n8n-nodes-base.googleSheets",
      "typeVersion": 4.7,
      "position": [
        224,
        16
      ],
      "id": "8ad6aef9-6ef1-4f16-a25a-5f2d54bc15e6",
      "name": "Update row in sheet",
      "credentials": {
        "googleSheetsOAuth2Api": {
          "id": "vuugbC8pFk62rio0",
          "name": "Google Sheets account"
        }
      }
    }
  ],
  "pinData": {},
  "connections": {
    "When clicking ‘Execute workflow’": {
      "main": [
        [
          {
            "node": "Get row(s) in sheet",
            "type": "main",
            "index": 0
          }
        ]
      ]
    },
    "Schedule Trigger": {
      "main": [
        [
          {
            "node": "Get row(s) in sheet",
            "type": "main",
            "index": 0
          }
        ]
      ]
    },
    "Get row(s) in sheet": {
      "main": [
        [
          {
            "node": "Search files and folders",
            "type": "main",
            "index": 0
          }
        ]
      ]
    },
    "Search files and folders": {
      "main": [
        [
          {
            "node": "Download file",
            "type": "main",
            "index": 0
          }
        ]
      ]
    },
    "Download file": {
      "main": [
        [
          {
            "node": "Upload a video",
            "type": "main",
            "index": 0
          }
        ]
      ]
    },
    "Upload a video": {
      "main": [
        [
          {
            "node": "Update row in sheet",
            "type": "main",
            "index": 0
          }
        ]
      ]
    }
  },
  "active": false,
  "settings": {
    "executionOrder": "v1"
  },
  "versionId": "1dae4596-1faf-4efb-8eef-73790524f2d6",
  "meta": {
    "templateCredsSetupCompleted": true,
    "instanceId": "e34d4f16fd2f73d4f82dded53241303230640f99a43dcf2acc68045772a5eafb"
  },
  "id": "vFIlJsabedrrwn12",
  "tags": []
}